rtl/01_mux2.sv
`timescale 1ns/1ps

// ============================================================
// Exercise 1 — mux2
// A 2-to-1 multiplexer: the single most-used building block
// in a CPU datapath. Every "choose between two values" decision
// inside a processor is one of these.
//
// Written twice on purpose:
//   mux2_structural — wired up from primitive gates
//   mux2_behavioral — described by what it DOES
// Both synthesise to the same hardware. Prove it in the waveform.
// ============================================================

// ---- Structural: you are literally drawing the circuit ----
module mux2_structural (
    input  logic a,     // input 0
    input  logic b,     // input 1
    input  logic sel,   // 0 -> a, 1 -> b
    output wire y
);
    wire nsel, a_and, b_and;

    not  u_not  (nsel,  sel);
    and  u_a    (a_and, a, nsel);
    and  u_b    (b_and, b, sel);
    or   u_out  (y,     a_and, b_and);
endmodule


// ---- Behavioral: you describe intent, the tool infers the gates ----
module mux2_behavioral (
    input  logic a,
    input  logic b,
    input  logic sel,
    output logic y
);
    // always_comb = "this block describes combinational logic".
    // Inside combinational blocks use blocking assignment: =
    always_comb begin
        if (sel) y = b;
        else     y = a;
    end
endmodule

01_tb_mux2.sv
// ============================================================
// Testbench for mux2
//
// Note what this is NOT: it is not "run it and eyeball the output".
// It drives every possible input combination, computes the expected
// answer independently, and fails loudly on mismatch.
//
// That is the habit to build from day one.
// ============================================================
`timescale 1ns/1ps

module tb_mux2;

    logic a, b, sel;
    logic y_struct, y_behav;
    logic expected;
    int   errors = 0;

    mux2_structural u_struct (.a(a), .b(b), .sel(sel), .y(y_struct));
    mux2_behavioral u_behav  (.a(a), .b(b), .sel(sel), .y(y_behav));

    initial begin
        // Dump waveforms so you can open this in GTKWave
        $dumpfile("build/mux2.vcd");
        $dumpvars(0, tb_mux2);

        // 3 inputs -> 8 combinations. Exhaustive proof, not spot-checking.
        for (int i = 0; i < 8; i++) begin
            {sel, b, a} = i[2:0];
            #10;  // let the logic settle, and make the waveform readable

            // The "golden model": what SHOULD the answer be?
            expected = sel ? b : a;

            if (y_behav !== expected) begin
                $display("FAIL behavioral: a=%b b=%b sel=%b -> got %b, want %b",
                         a, b, sel, y_behav, expected);
                errors++;
            end
            if (y_struct !== y_behav) begin
                $display("FAIL structural != behavioral: a=%b b=%b sel=%b -> %b vs %b",
                         a, b, sel, y_struct, y_behav);
                errors++;
            end
        end

        if (errors == 0) $display("PASS  mux2: 8/8 combinations correct");
        else             $display("FAIL  mux2: %0d error(s)", errors);
        $finish;
    end

endmodule

build/mux2.vcd
$date
	Mon Aug 24 12:52:00 2026
$end
$version
	Icarus Verilog
$end
$timescale
	1ps
$end
$scope module tb_mux2 $end
$var wire 1 ! y_struct $end
$var wire 1 " y_behav $end
$var reg 1 # a $end
$var reg 1 $ b $end
$var reg 1 % expected $end
$var reg 1 & sel $end
$var integer 32 ' errors [31:0] $end
$scope module u_behav $end
$var wire 1 # a $end
$var wire 1 $ b $end
$var wire 1 & sel $end
$var reg 1 " y $end
$upscope $end
$scope module u_struct $end
$var wire 1 # a $end
$var wire 1 ( a_and $end
$var wire 1 $ b $end
$var wire 1 ) b_and $end
$var wire 1 * nsel $end
$var wire 1 & sel $end
$var wire 1 ! y $end
$upscope $end
$scope begin $ivl_for_loop0 $end
$var integer 32 + i [31:0] $end
$upscope $end
$upscope $end
$enddefinitions $end
$comment Show the parameter values. $end
$dumpall
$end
#0
$dumpvars
b0 +
1*
0)
0(
b0 '
0&
x%
0$
0#
0"
0!
$end
#10000
1!
1"
1(
1#
b1 +
0%
#20000
0!
0"
0(
1$
0#
b10 +
1%
#30000
1!
1"
1(
1#
b11 +
0%
#40000
0!
0*
0"
0(
1&
0$
0#
b100 +
1%
#50000
1#
b101 +
0%
#60000
1!
1)
1"
1$
0#
b110 +
#70000
1#
b111 +
1%
#80000
b1000 +
