rtl/02_adder.sv
`timescale 1ns/1ps

// ============================================================
// Exercise 2 — full adder -> ripple-carry adder
//
// This is the first time you build a big thing out of small
// identical things. That pattern never stops: adder from full
// adders, ALU from adders, CPU from ALU + register file + control.
// ============================================================

module full_adder (
    input  logic a,
    input  logic b,
    input  logic cin,
    output logic sum,
    output logic cout
);
    assign sum  = a ^ b ^ cin;
    assign cout = (a & b) | (cin & (a ^ b));
endmodule


// Parameterised: WIDTH is a compile-time constant, not a runtime value.
// Change it to 32 later and this same file becomes your CPU's adder.
module ripple_adder #(
    parameter int WIDTH = 4
) (
    input  logic [WIDTH-1:0] a,
    input  logic [WIDTH-1:0] b,
    input  logic             cin,
    output logic [WIDTH-1:0] sum,
    output logic             cout
);
    logic [WIDTH:0] carry;
    assign carry[0] = cin;

    // generate: "stamp out WIDTH copies of this module at elaboration time"
    genvar i;
    generate
        for (i = 0; i < WIDTH; i++) begin : g_bit
            full_adder u_fa (
                .a    (a[i]),
                .b    (b[i]),
                .cin  (carry[i]),
                .sum  (sum[i]),
                .cout (carry[i+1])
            );
        end
    endgenerate

    assign cout = carry[WIDTH];
endmodule

02_tb_adder.sv
// ============================================================
// Testbench for ripple_adder
//
// 4 bits + 4 bits + carry = 512 cases. Small enough to test
// exhaustively — so do it. Exhaustive beats clever every time
// it is affordable.
// ============================================================
`timescale 1ns/1ps

module tb_adder;

    localparam int WIDTH = 4;

    logic [WIDTH-1:0] a, b, sum;
    logic             cin, cout;
    logic [WIDTH:0]   got;
    int               exp;
    int               errors = 0;

    ripple_adder #(.WIDTH(WIDTH)) u_add (
        .a(a), .b(b), .cin(cin), .sum(sum), .cout(cout)
    );

    initial begin
        $dumpfile("build/adder.vcd");
        $dumpvars(0, tb_adder);

        for (int ia = 0; ia < (1 << WIDTH); ia++) begin
            for (int ib = 0; ib < (1 << WIDTH); ib++) begin
                for (int ic = 0; ic < 2; ic++) begin
                    a   = ia[WIDTH-1:0];
                    b   = ib[WIDTH-1:0];
                    cin = ic[0];
                    #1;

                    // Golden model: plain integer arithmetic.
                    // Your hardware must match ordinary maths.
                    exp = ia + ib + ic;
                    got = {cout, sum};

                    if (got !== exp[WIDTH:0]) begin
                        $display("FAIL: %0d + %0d + %0d -> got %0d, want %0d",
                                 ia, ib, ic, got, exp);
                        errors++;
                    end
                end
            end
        end

        if (errors == 0) $display("PASS  ripple_adder: 512/512 cases correct");
        else             $display("FAIL  ripple_adder: %0d error(s)", errors);
        $finish;
    end

endmodule

docs/bugs/0002-adder-unknown/broken.vcd
$date
	Wed Sep 16 07:06:33 2026
$end
$version
	Icarus Verilog
$end
$timescale
	1ps
$end
$scope module tb_adder $end
$var wire 4 ! sum [3:0] $end
$var wire 1 " cout $end
$var parameter 32 # WIDTH $end
$var reg 4 $ a [3:0] $end
$var reg 4 % b [3:0] $end
$var reg 1 & cin $end
$var reg 5 ' got [4:0] $end
$var integer 32 ( errors [31:0] $end
$var integer 32 ) exp [31:0] $end
$scope module u_add $end
$var wire 4 * a [3:0] $end
$var wire 4 + b [3:0] $end
$var wire 1 & cin $end
$var wire 4 , sum [3:0] $end
$var wire 1 " cout $end
$var wire 5 - carry [4:0] $end
$var parameter 32 . WIDTH $end
$scope begin g_bit[0] $end
$var parameter 2 / i $end
$scope module u_fa $end
$var wire 1 0 a $end
$var wire 1 1 b $end
$var wire 1 2 cin $end
$var wire 1 3 cout $end
$var wire 1 4 sum $end
$upscope $end
$upscope $end
$scope begin g_bit[1] $end
$var parameter 2 5 i $end
$scope module u_fa $end
$var wire 1 6 a $end
$var wire 1 7 b $end
$var wire 1 8 cin $end
$var wire 1 9 cout $end
$var wire 1 : sum $end
$upscope $end
$upscope $end
$scope begin g_bit[2] $end
$var parameter 3 ; i $end
$scope module u_fa $end
$var wire 1 < a $end
$var wire 1 = b $end
$var wire 1 > cin $end
$var wire 1 ? cout $end
$var wire 1 @ sum $end
$upscope $end
$upscope $end
$scope begin g_bit[3] $end
$var parameter 3 A i $end
$scope module u_fa $end
$var wire 1 B a $end
$var wire 1 C b $end
$var wire 1 D cin $end
$var wire 1 E cout $end
$var wire 1 F sum $end
$upscope $end
$upscope $end
$upscope $end
$scope begin $ivl_for_loop0 $end
$var integer 32 G ia [31:0] $end
$scope begin $ivl_for_loop1 $end
$var integer 32 H ib [31:0] $end
$scope begin $ivl_for_loop2 $end
$var integer 32 I ic [31:0] $end
$upscope $end
$upscope $end
$upscope $end
$upscope $end
$enddefinitions $end
$comment Show the parameter values. $end
$dumpall
b11 A
b10 ;
b1 5
b0 /
b100 .
b100 #
$end
#0
$dumpvars
b0 I
b0 H
b0 G
0F
0E
0D
0C
0B
0@
0?
0>
0=
0<
0:
09
08
07
06
04
03
02
01
00
b0 -
b0 ,
b0 +
b0 *
b0 )
b0 (
bx '
0&
b0 %
b0 $
0"
b0 !
$end
#1000
b1 !
b1 ,
14
12
b1 -
1&
b1 I
b0 '
#2000
0:
08
b1 !
b1 ,
03
02
14
b0 -
11
0&
b1 %
b1 +
b1 H
b0 I
b1 '
b1 )
#3000
1:
18
b10 !
b10 ,
13
04
12
b11 -
1&
b1 I
#4000
0@
0>
08
03
b10 !
b10 ,
09
02
04
1:
b0 -
01
17
0&
b10 %
b10 +
b10 H
b0 I
b10 '
b10 )
#5000
b11 !
b11 ,
14
12
b1 -
1&
b1 I
#6000
0@
0>
09
1:
08
b11 !
b11 ,
03
02
14
b0 -
11
0&
b11 %
b11 +
b11 H
b0 I
b11 '
b11 )
#7000
1@
1>
19
0:
18
b100 !
b100 ,
13
04
12
b111 -
1&
b1 I
#8000
0F
0"
0D
0>
08
03
09
b100 !
b100 ,
0?
02
04
0:
1@
b0 -
01
07
1=
0&
b100 %
b100 +
b100 H
b0 I
b100 '
b100 )
#9000
b101 !
b101 ,
14
12
b1 -
1&
b1 I
#10000
0:
08
b101 !
b101 ,
03
02
14
b0 -
11
0&
b101 %
b101 +
b101 H
b0 I
b101 '
b101 )
#11000
1:
18
b110 !
b110 ,
13
04
12
b11 -
1&
b1 I
#12000
0F
0"
0D
0?
1@
0>
08
03
b110 !
b110 ,
09
02
04
1:
b0 -
01
17
0&
b110 %
b110 +
b110 H
b0 I
b110 '
b110 )
#13000
b111 !
b111 ,
14
12
b1 -
1&
b1 I
#14000
0F
0"
0D
0?
1@
0>
09
1:
08
b111 !
b111 ,
03
02
14
b0 -
11
0&
b111 %
b111 +
b111 H
b0 I
b111 '
b111 )
#15000
1F
1"
1D
1?
0@
1>
19
0:
18
b1000 !
b1000 ,
13
04
12
b1111 -
1&
b1 I
#16000
0"
0D
0>
08
03
09
0?
b1000 !
b1000 ,
0E
02
04
0:
0@
1F
b0 -
01
07
0=
1C
0&
b1000 %
b1000 +
b1000 H
b0 I
b1 (
b11000 '
b1000 )
#17000
b1001 !
b1001 ,
14
12
b1 -
1&
b1 I
b1000 '
#18000
0:
08
b1001 !
b1001 ,
03
02
14
b0 -
11
0&
b1001 %
b1001 +
b1001 H
b0 I
b1001 '
b1001 )
#19000
1:
18
b1010 !
b1010 ,
13
04
12
b11 -
1&
b1 I
#20000
0@
0>
08
03
b1010 !
b1010 ,
09
02
04
1:
b0 -
01
17
0&
b1010 %
b1010 +
b1010 H
b0 I
b1010 '
b1010 )
#21000
b1011 !
b1011 ,
14
12
b1 -
1&
b1 I
#22000
0@
0>
09
1:
08
b1011 !
b1011 ,
03
02
14
b0 -
11
0&
b1011 %
b1011 +
b1011 H
b0 I
b1011 '
b1011 )
#23000
1@
1>
19
0:
18
b1100 !
b1100 ,
13
04
12
b111 -
1&
b1 I
#24000
0E
1F
0"
0D
0>
08
03
09
b1100 !
b1100 ,
0?
02
04
0:
1@
b0 -
01
07
1=
0&
b1100 %
b1100 +
b1100 H
b0 I
b1100 '
b1100 )
#25000
b1101 !
b1101 ,
14
12
b1 -
1&
b1 I
#26000
0:
08
b1101 !
b1101 ,
03
02
14
b0 -
11
0&
b1101 %
b1101 +
b1101 H
b0 I
b1101 '
b1101 )
#27000
1:
18
b1110 !
b1110 ,
13
04
12
b11 -
1&
b1 I
#28000
0E
1F
0"
0D
0?
1@
0>
08
03
b1110 !
b1110 ,
09
02
04
1:
b0 -
01
17
0&
b1110 %
b1110 +
b1110 H
b0 I
b1110 '
b1110 )
#29000
b1111 !
b1111 ,
14
12
b1 -
1&
b1 I
#30000
0E
1F
0"
0D
0?
1@
0>
09
1:
08
b1111 !
b1111 ,
03
02
14
b0 -
11
0&
b1111 %
b1111 +
b1111 H
b0 I
b1111 '
b1111 )
#31000
1E
0F
1"
1D
1?
0@
1>
19
0:
18
b0 !
b0 ,
13
04
12
b11111 -
1&
b1 I
#32000
08
0"
0D
0>
03
14
09
0?
b1 !
b1 ,
0E
02
0:
0@
0F
b0 -
01
07
0=
0C
10
0&
b0 %
b0 +
b1 $
b1 *
b1 G
b0 H
b0 I
b10000 '
b10000 )
#33000
1:
18
b10 !
b10 ,
13
04
12
b11 -
1&
b1 I
b1 '
b1 )
#34000
b10 !
b10 ,
02
04
b10 -
11
0&
b1 %
b1 +
b1 H
b0 I
b10 '
b10 )
#35000
b11 !
b11 ,
14
12
b11 -
1&
b1 I
#36000
08
0@
0>
03
b11 !
b11 ,
09
02
14
1:
b0 -
01
17
0&
b10 %
b10 +
b10 H
b0 I
b11 '
b11 )
#37000
1@
1>
19
0:
18
b100 !
b100 ,
13
04
12
b111 -
1&
b1 I
#38000
b100 !
b100 ,
02
04
b110 -
11
0&
b11 %
b11 +
b11 H
b0 I
b100 '
b100 )
#39000
b101 !
b101 ,
14
12
b111 -
1&
b1 I
#40000
08
0F
0"
0D
0>
03
09
b101 !
b101 ,
0?
02
14
0:
1@
b0 -
01
07
1=
0&
b100 %
b100 +
b100 H
b0 I
b101 '
b101 )
#41000
1:
18
b110 !
b110 ,
13
04
12
b11 -
1&
b1 I
#42000
b110 !
b110 ,
02
04
b10 -
11
0&
b101 %
b101 +
b101 H
b0 I
b110 '
b110 )
#43000
b111 !
b111 ,
14
12
b11 -
1&
b1 I
#44000
0F
0"
0D
0?
08
1@
0>
03
b111 !
b111 ,
09
02
14
1:
b0 -
01
17
0&
b110 %
b110 +
b110 H
b0 I
b111 '
b111 )
#45000
1F
1"
1D
1?
0@
1>
19
0:
18
b1000 !
b1000 ,
13
04
12
b1111 -
1&
b1 I
#46000
b1000 !
b1000 ,
02
04
b1110 -
11
0&
b111 %
b111 +
b111 H
b0 I
b10 (
b11000 '
b1000 )
#47000
b1001 !
b1001 ,
14
12
b1111 -
1&
b1 I
b11 (
#48000
08
0"
0D
0>
03
09
0?
b1001 !
b1001 ,
0E
02
14
0:
0@
1F
b0 -
01
07
0=
1C
0&
b1000 %
b1000 +
b1000 H
b0 I
b100 (
b11001 '
b1001 )
#49000
1:
18
b1010 !
b1010 ,
13
04
12
b11 -
1&
b1 I
b1001 '
#50000
b1010 !
b1010 ,
02
04
b10 -
11
0&
b1001 %
b1001 +
b1001 H
b0 I
b1010 '
b1010 )
#51000
b1011 !
b1011 ,
14
12
b11 -
1&
b1 I
#52000
08
0@
0>
03
b1011 !
b1011 ,
09
02
14
1:
b0 -
01
17
0&
b1010 %
b1010 +
b1010 H
b0 I
b1011 '
b1011 )
#53000
1@
1>
19
0:
18
b1100 !
b1100 ,
13
04
12
b111 -
1&
b1 I
#54000
b1100 !
b1100 ,
02
04
b110 -
11
0&
b1011 %
b1011 +
b1011 H
b0 I
b1100 '
b1100 )
#55000
b1101 !
b1101 ,
14
12
b111 -
1&
b1 I
#56000
0E
08
1F
0"
0D
0>
03
09
b1101 !
b1101 ,
0?
02
14
0:
1@
b0 -
01
07
1=
0&
b1100 %
b1100 +
b1100 H
b0 I
b1101 '
b1101 )
#57000
1:
18
b1110 !
b1110 ,
13
04
12
b11 -
1&
b1 I
#58000
b1110 !
b1110 ,
02
04
b10 -
11
0&
b1101 %
b1101 +
b1101 H
b0 I
b1110 '
b1110 )
#59000
b1111 !
b1111 ,
14
12
b11 -
1&
b1 I
#60000
0E
1F
0"
0D
0?
08
1@
0>
03
b1111 !
b1111 ,
09
02
14
1:
b0 -
01
17
0&
b1110 %
b1110 +
b1110 H
b0 I
b1111 '
b1111 )
#61000
1E
0F
1"
1D
1?
0@
1>
19
0:
18
b0 !
b0 ,
13
04
12
b11111 -
1&
b1 I
#62000
b0 !
b0 ,
02
04
b11110 -
11
0&
b1111 %
b1111 +
b1111 H
b0 I
b10000 '
b10000 )
#63000
b1 !
b1 ,
14
12
b11111 -
1&
b1 I
#64000
0>
09
0"
0D
1:
08
04
0?
b10 !
b10 ,
0E
02
0@
0F
03
b0 -
01
07
0=
0C
00
16
0&
b0 %
b0 +
b10 $
b10 *
b10 G
b0 H
b0 I
b10001 '
b10001 )
#65000
b11 !
b11 ,
14
12
b1 -
1&
b1 I
b10 '
b10 )
#66000
0@
0>
09
1:
08
b11 !
b11 ,
03
02
14
b0 -
11
0&
b1 %
b1 +
b1 H
b0 I
b11 '
b11 )
#67000
1@
1>
19
0:
18
b100 !
b100 ,
13
04
12
b111 -
1&
b1 I
#68000
08
03
b100 !
b100 ,
02
04
0:
b100 -
01
17
0&
b10 %
b10 +
b10 H
b0 I
b100 '
b100 )
#69000
b101 !
b101 ,
14
12
b101 -
1&
b1 I
#70000
0:
08
b101 !
b101 ,
03
02
14
b100 -
11
0&
b11 %
b11 +
b11 H
b0 I
b101 '
b101 )
#71000
1:
18
b110 !
b110 ,
13
04
12
b111 -
1&
b1 I
#72000
0>
09
0F
0"
0D
08
03
b110 !
b110 ,
0?
02
04
1:
1@
b0 -
01
07
1=
0&
b100 %
b100 +
b100 H
b0 I
b110 '
b110 )
#73000
b111 !
b111 ,
14
12
b1 -
1&
b1 I
#74000
0F
0"
0D
0?
1@
0>
09
1:
08
b111 !
b111 ,
03
02
14
b0 -
11
0&
b101 %
b101 +
b101 H
b0 I
b111 '
b111 )
#75000
1F
1"
1D
1?
0@
1>
19
0:
18
b1000 !
b1000 ,
13
04
12
b1111 -
1&
b1 I
#76000
08
03
b1000 !
b1000 ,
02
04
0:
b1100 -
01
17
0&
b110 %
b110 +
b110 H
b0 I
b101 (
b11000 '
b1000 )
#77000
b1001 !
b1001 ,
14
12
b1101 -
1&
b1 I
b110 (
#78000
0:
08
b1001 !
b1001 ,
03
02
14
b1100 -
11
0&
b111 %
b111 +
b111 H
b0 I
b111 (
b11001 '
b1001 )
#79000
1:
18
b1010 !
b1010 ,
13
04
12
b1111 -
1&
b1 I
b1000 (
#80000
0>
09
0"
0D
08
03
0?
b1010 !
b1010 ,
0E
02
04
1:
0@
1F
b0 -
01
07
0=
1C
0&
b1000 %
b1000 +
b1000 H
b0 I
b1001 (
b11010 '
b1010 )
#81000
b1011 !
b1011 ,
14
12
b1 -
1&
b1 I
b1010 '
#82000
0@
0>
09
1:
08
b1011 !
b1011 ,
03
02
14
b0 -
11
0&
b1001 %
b1001 +
b1001 H
b0 I
b1011 '
b1011 )
#83000
1@
1>
19
0:
18
b1100 !
b1100 ,
13
04
12
b111 -
1&
b1 I
#84000
08
03
b1100 !
b1100 ,
02
04
0:
b100 -
01
17
0&
b1010 %
b1010 +
b1010 H
b0 I
b1100 '
b1100 )
#85000
b1101 !
b1101 ,
14
12
b101 -
1&
b1 I
#86000
0:
08
b1101 !
b1101 ,
03
02
14
b100 -
11
0&
b1011 %
b1011 +
b1011 H
b0 I
b1101 '
b1101 )
#87000
1:
18
b1110 !
b1110 ,
13
04
12
b111 -
1&
b1 I
#88000
0>
0E
09
1F
0"
0D
08
03
b1110 !
b1110 ,
0?
02
04
1:
1@
b0 -
01
07
1=
0&
b1100 %
b1100 +
b1100 H
b0 I
b1110 '
b1110 )
#89000
b1111 !
b1111 ,
14
12
b1 -
1&
b1 I
#90000
0E
1F
0"
0D
0?
1@
0>
09
1:
08
b1111 !
b1111 ,
03
02
14
b0 -
11
0&
b1101 %
b1101 +
b1101 H
b0 I
b1111 '
b1111 )
#91000
1E
0F
1"
1D
1?
0@
1>
19
0:
18
b0 !
b0 ,
13
04
12
b11111 -
1&
b1 I
#92000
08
03
b0 !
b0 ,
02
04
0:
b11100 -
01
17
0&
b1110 %
b1110 +
b1110 H
b0 I
b10000 '
b10000 )
#93000
b1 !
b1 ,
14
12
b11101 -
1&
b1 I
#94000
0:
08
b1 !
b1 ,
03
02
14
b11100 -
11
0&
b1111 %
b1111 +
b1111 H
b0 I
b10001 '
b10001 )
#95000
1:
18
b10 !
b10 ,
13
04
12
b11111 -
1&
b1 I
#96000
0>
09
08
0"
0D
03
14
0?
b11 !
b11 ,
0E
02
1:
0@
0F
b0 -
01
07
0=
0C
10
0&
b0 %
b0 +
b11 $
b11 *
b11 G
b0 H
b0 I
b10010 '
b10010 )
#97000
1@
1>
19
0:
18
b100 !
b100 ,
13
04
12
b111 -
1&
b1 I
b11 '
b11 )
#98000
b100 !
b100 ,
02
04
b110 -
11
0&
b1 %
b1 +
b1 H
b0 I
b100 '
b100 )
#99000
b101 !
b101 ,
14
12
b111 -
1&
b1 I
#100000
08
03
b101 !
b101 ,
02
14
0:
b100 -
01
17
0&
b10 %
b10 +
b10 H
b0 I
b101 '
b101 )
#101000
1:
18
b110 !
b110 ,
13
04
12
b111 -
1&
b1 I
#102000
b110 !
b110 ,
02
04
b110 -
11
0&
b11 %
b11 +
b11 H
b0 I
b110 '
b110 )
#103000
b111 !
b111 ,
14
12
b111 -
1&
b1 I
#104000
0>
09
08
0F
0"
0D
03
b111 !
b111 ,
0?
02
14
1:
1@
b0 -
01
07
1=
0&
b100 %
b100 +
b100 H
b0 I
b111 '
b111 )
#105000
1F
1"
1D
1?
0@
1>
19
0:
18
b1000 !
b1000 ,
13
04
12
b1111 -
1&
b1 I
#106000
b1000 !
b1000 ,
02
04
b1110 -
11
0&
b101 %
b101 +
b101 H
b0 I
b1010 (
b11000 '
b1000 )
#107000
b1001 !
b1001 ,
14
12
b1111 -
1&
b1 I
b1011 (
#108000
08
03
b1001 !
b1001 ,
02
14
0:
b1100 -
01
17
0&
b110 %
b110 +
b110 H
b0 I
b1100 (
b11001 '
b1001 )
#109000
1:
18
b1010 !
b1010 ,
13
04
12
b1111 -
1&
b1 I
b1101 (
#110000
b1010 !
b1010 ,
02
04
b1110 -
11
0&
b111 %
b111 +
b111 H
b0 I
b1110 (
b11010 '
b1010 )
#111000
b1011 !
b1011 ,
14
12
b1111 -
1&
b1 I
b1111 (
#112000
0>
09
08
0"
0D
03
0?
b1011 !
b1011 ,
0E
02
14
1:
0@
1F
b0 -
01
07
0=
1C
0&
b1000 %
b1000 +
b1000 H
b0 I
b10000 (
b11011 '
b1011 )
#113000
1@
1>
19
0:
18
b1100 !
b1100 ,
13
04
12
b111 -
1&
b1 I
b1011 '
#114000
b1100 !
b1100 ,
02
04
b110 -
11
0&
b1001 %
b1001 +
b1001 H
b0 I
b1100 '
b1100 )
#115000
b1101 !
b1101 ,
14
12
b111 -
1&
b1 I
#116000
08
03
b1101 !
b1101 ,
02
14
0:
b100 -
01
17
0&
b1010 %
b1010 +
b1010 H
b0 I
b1101 '
b1101 )
#117000
1:
18
b1110 !
b1110 ,
13
04
12
b111 -
1&
b1 I
#118000
b1110 !
b1110 ,
02
04
b110 -
11
0&
b1011 %
b1011 +
b1011 H
b0 I
b1110 '
b1110 )
#119000
b1111 !
b1111 ,
14
12
b111 -
1&
b1 I
#120000
0>
09
0E
08
1F
0"
0D
03
b1111 !
b1111 ,
0?
02
14
1:
1@
b0 -
01
07
1=
0&
b1100 %
b1100 +
b1100 H
b0 I
b1111 '
b1111 )
#121000
1E
0F
1"
1D
1?
0@
1>
19
0:
18
b0 !
b0 ,
13
04
12
b11111 -
1&
b1 I
#122000
b0 !
b0 ,
02
04
b11110 -
11
0&
b1101 %
b1101 +
b1101 H
b0 I
b10000 '
b10000 )
#123000
b1 !
b1 ,
14
12
b11111 -
1&
b1 I
#124000
08
03
b1 !
b1 ,
02
14
0:
b11100 -
01
17
0&
b1110 %
b1110 +
b1110 H
b0 I
b10001 '
b10001 )
#125000
1:
18
b10 !
b10 ,
13
04
12
b11111 -
1&
b1 I
#126000
b10 !
b10 ,
02
04
b11110 -
11
0&
b1111 %
b1111 +
b1111 H
b0 I
b10010 '
b10010 )
#127000
b11 !
b11 ,
14
12
b11111 -
1&
b1 I
#128000
0"
0D
0?
1@
0:
0>
08
04
b100 !
b100 ,
0E
02
0F
03
09
b0 -
01
07
0=
0C
00
06
1<
0&
b0 %
b0 +
b100 $
b100 *
b100 G
b0 H
b0 I
b10011 '
b10011 )
#129000
b101 !
b101 ,
14
12
b1 -
1&
b1 I
b100 '
b100 )
#130000
0:
08
b101 !
b101 ,
03
02
14
b0 -
11
0&
b1 %
b1 +
b1 H
b0 I
b101 '
b101 )
#131000
1:
18
b110 !
b110 ,
13
04
12
b11 -
1&
b1 I
#132000
0F
0"
0D
0?
1@
0>
08
03
b110 !
b110 ,
09
02
04
1:
b0 -
01
17
0&
b10 %
b10 +
b10 H
b0 I
b110 '
b110 )
#133000
b111 !
b111 ,
14
12
b1 -
1&
b1 I
#134000
0F
0"
0D
0?
1@
0>
09
1:
08
b111 !
b111 ,
03
02
14
b0 -
11
0&
b11 %
b11 +
b11 H
b0 I
b111 '
b111 )
#135000
1F
1"
1D
1?
0@
1>
19
0:
18
b1000 !
b1000 ,
13
04
12
b1111 -
1&
b1 I
#136000
0>
08
03
09
b1000 !
b1000 ,
02
04
0:
0@
b1000 -
01
07
1=
0&
b100 %
b100 +
b100 H
b0 I
b10001 (
b11000 '
b1000 )
#137000
b1001 !
b1001 ,
14
12
b1001 -
1&
b1 I
b10010 (
#138000
0:
08
b1001 !
b1001 ,
03
02
14
b1000 -
11
0&
b101 %
b101 +
b101 H
b0 I
b10011 (
b11001 '
b1001 )
#139000
1:
18
b1010 !
b1010 ,
13
04
12
b1011 -
1&
b1 I
b10100 (
#140000
0@
0>
08
03
b1010 !
b1010 ,
09
02
04
1:
b1000 -
01
17
0&
b110 %
b110 +
b110 H
b0 I
b10101 (
b11010 '
b1010 )
#141000
b1011 !
b1011 ,
14
12
b1001 -
1&
b1 I
b10110 (
#142000
0@
0>
09
1:
08
b1011 !
b1011 ,
03
02
14
b1000 -
11
0&
b111 %
b111 +
b111 H
b0 I
b10111 (
b11011 '
b1011 )
#143000
1@
1>
19
0:
18
b1100 !
b1100 ,
13
04
12
b1111 -
1&
b1 I
b11000 (
#144000
0"
0D
0?
0>
08
03
09
b1100 !
b1100 ,
0E
02
04
0:
1@
1F
b0 -
01
07
0=
1C
0&
b1000 %
b1000 +
b1000 H
b0 I
b11001 (
b11100 '
b1100 )
#145000
b1101 !
b1101 ,
14
12
b1 -
1&
b1 I
b1100 '
#146000
0:
08
b1101 !
b1101 ,
03
02
14
b0 -
11
0&
b1001 %
b1001 +
b1001 H
b0 I
b1101 '
b1101 )
#147000
1:
18
b1110 !
b1110 ,
13
04
12
b11 -
1&
b1 I
#148000
0E
1F
0"
0D
0?
1@
0>
08
03
b1110 !
b1110 ,
09
02
04
1:
b0 -
01
17
0&
b1010 %
b1010 +
b1010 H
b0 I
b1110 '
b1110 )
#149000
b1111 !
b1111 ,
14
12
b1 -
1&
b1 I
#150000
0E
1F
0"
0D
0?
1@
0>
09
1:
08
b1111 !
b1111 ,
03
02
14
b0 -
11
0&
b1011 %
b1011 +
b1011 H
b0 I
b1111 '
b1111 )
#151000
1E
0F
1"
1D
1?
0@
1>
19
0:
18
b0 !
b0 ,
13
04
12
b11111 -
1&
b1 I
#152000
0>
08
03
09
b0 !
b0 ,
02
04
0:
0@
b11000 -
01
07
1=
0&
b1100 %
b1100 +
b1100 H
b0 I
b10000 '
b10000 )
#153000
b1 !
b1 ,
14
12
b11001 -
1&
b1 I
#154000
0:
08
b1 !
b1 ,
03
02
14
b11000 -
11
0&
b1101 %
b1101 +
b1101 H
b0 I
b10001 '
b10001 )
#155000
1:
18
b10 !
b10 ,
13
04
12
b11011 -
1&
b1 I
#156000
0@
0>
08
03
b10 !
b10 ,
09
02
04
1:
b11000 -
01
17
0&
b1110 %
b1110 +
b1110 H
b0 I
b10010 '
b10010 )
#157000
b11 !
b11 ,
14
12
b11001 -
1&
b1 I
#158000
0@
0>
09
1:
08
b11 !
b11 ,
03
02
14
b11000 -
11
0&
b1111 %
b1111 +
b1111 H
b0 I
b10011 '
b10011 )
#159000
1@
1>
19
0:
18
b100 !
b100 ,
13
04
12
b11111 -
1&
b1 I
#160000
0"
0D
0?
08
0>
03
14
09
b101 !
b101 ,
0E
02
0:
1@
0F
b0 -
01
07
0=
0C
10
0&
b0 %
b0 +
b101 $
b101 *
b101 G
b0 H
b0 I
b10100 '
b10100 )
#161000
1:
18
b110 !
b110 ,
13
04
12
b11 -
1&
b1 I
b101 '
b101 )
#162000
b110 !
b110 ,
02
04
b10 -
11
0&
b1 %
b1 +
b1 H
b0 I
b110 '
b110 )
#163000
b111 !
b111 ,
14
12
b11 -
1&
b1 I
#164000
0F
0"
0D
0?
08
1@
0>
03
b111 !
b111 ,
09
02
14
1:
b0 -
01
17
0&
b10 %
b10 +
b10 H
b0 I
b111 '
b111 )
#165000
1F
1"
1D
1?
0@
1>
19
0:
18
b1000 !
b1000 ,
13
04
12
b1111 -
1&
b1 I
#166000
b1000 !
b1000 ,
02
04
b1110 -
11
0&
b11 %
b11 +
b11 H
b0 I
b11010 (
b11000 '
b1000 )
#167000
b1001 !
b1001 ,
14
12
b1111 -
1&
b1 I
b11011 (
#168000
08
0>
03
09
b1001 !
b1001 ,
02
14
0:
0@
b1000 -
01
07
1=
0&
b100 %
b100 +
b100 H
b0 I
b11100 (
b11001 '
b1001 )
#169000
1:
18
b1010 !
b1010 ,
13
04
12
b1011 -
1&
b1 I
b11101 (
#170000
b1010 !
b1010 ,
02
04
b1010 -
11
0&
b101 %
b101 +
b101 H
b0 I
b11110 (
b11010 '
b1010 )
#171000
b1011 !
b1011 ,
14
12
b1011 -
1&
b1 I
b11111 (
#172000
08
0@
0>
03
b1011 !
b1011 ,
09
02
14
1:
b1000 -
01
17
0&
b110 %
b110 +
b110 H
b0 I
b100000 (
b11011 '
b1011 )
#173000
1@
1>
19
0:
18
b1100 !
b1100 ,
13
04
12
b1111 -
1&
b1 I
b100001 (
#174000
b1100 !
b1100 ,
02
04
b1110 -
11
0&
b111 %
b111 +
b111 H
b0 I
b100010 (
b11100 '
b1100 )
#175000
b1101 !
b1101 ,
14
12
b1111 -
1&
b1 I
b100011 (
#176000
0"
0D
0?
08
0>
03
09
b1101 !
b1101 ,
0E
02
14
0:
1@
1F
b0 -
01
07
0=
1C
0&
b1000 %
b1000 +
b1000 H
b0 I
b100100 (
b11101 '
b1101 )
#177000
1:
18
b1110 !
b1110 ,
13
04
12
b11 -
1&
b1 I
b1101 '
#178000
b1110 !
b1110 ,
02
04
b10 -
11
0&
b1001 %
b1001 +
b1001 H
b0 I
b1110 '
b1110 )
#179000
b1111 !
b1111 ,
14
12
b11 -
1&
b1 I
#180000
0E
1F
0"
0D
0?
08
1@
0>
03
b1111 !
b1111 ,
09
02
14
1:
b0 -
01
17
0&
b1010 %
b1010 +
b1010 H
b0 I
b1111 '
b1111 )
#181000
1E
0F
1"
1D
1?
0@
1>
19
0:
18
b0 !
b0 ,
13
04
12
b11111 -
1&
b1 I
#182000
b0 !
b0 ,
02
04
b11110 -
11
0&
b1011 %
b1011 +
b1011 H
b0 I
b10000 '
b10000 )
#183000
b1 !
b1 ,
14
12
b11111 -
1&
b1 I
#184000
08
0>
03
09
b1 !
b1 ,
02
14
0:
0@
b11000 -
01
07
1=
0&
b1100 %
b1100 +
b1100 H
b0 I
b10001 '
b10001 )
#185000
1:
18
b10 !
b10 ,
13
04
12
b11011 -
1&
b1 I
#186000
b10 !
b10 ,
02
04
b11010 -
11
0&
b1101 %
b1101 +
b1101 H
b0 I
b10010 '
b10010 )
#187000
b11 !
b11 ,
14
12
b11011 -
1&
b1 I
#188000
08
0@
0>
03
b11 !
b11 ,
09
02
14
1:
b11000 -
01
17
0&
b1110 %
b1110 +
b1110 H
b0 I
b10011 '
b10011 )
#189000
1@
1>
19
0:
18
b100 !
b100 ,
13
04
12
b11111 -
1&
b1 I
#190000
b100 !
b100 ,
02
04
b11110 -
11
0&
b1111 %
b1111 +
b1111 H
b0 I
b10100 '
b10100 )
#191000
b101 !
b101 ,
14
12
b11111 -
1&
b1 I
#192000
0"
0D
0?
0>
09
1:
08
04
b110 !
b110 ,
0E
02
1@
0F
03
b0 -
01
07
0=
0C
00
16
0&
b0 %
b0 +
b110 $
b110 *
b110 G
b0 H
b0 I
b10101 '
b10101 )
#193000
b111 !
b111 ,
14
12
b1 -
1&
b1 I
b110 '
b110 )
#194000
0F
0"
0D
0?
1@
0>
09
1:
08
b111 !
b111 ,
03
02
14
b0 -
11
0&
b1 %
b1 +
b1 H
b0 I
b111 '
b111 )
#195000
1F
1"
1D
1?
0@
1>
19
0:
18
b1000 !
b1000 ,
13
04
12
b1111 -
1&
b1 I
#196000
08
03
b1000 !
b1000 ,
02
04
0:
b1100 -
01
17
0&
b10 %
b10 +
b10 H
b0 I
b100101 (
b11000 '
b1000 )
#197000
b1001 !
b1001 ,
14
12
b1101 -
1&
b1 I
b100110 (
#198000
0:
08
b1001 !
b1001 ,
03
02
14
b1100 -
11
0&
b11 %
b11 +
b11 H
b0 I
b100111 (
b11001 '
b1001 )
#199000
1:
18
b1010 !
b1010 ,
13
04
12
b1111 -
1&
b1 I
b101000 (
#200000
0>
09
08
03
b1010 !
b1010 ,
02
04
1:
0@
b1000 -
01
07
1=
0&
b100 %
b100 +
b100 H
b0 I
b101001 (
b11010 '
b1010 )
#201000
b1011 !
b1011 ,
14
12
b1001 -
1&
b1 I
b101010 (
